EopTool/__init__.py
EopTool/__main__.py
EopTool/calc.py
EopTool/io.py
EopTool/units.py
EopTool/visualise.py
EopTool/interface/BoundedEntry.py
EopTool/interface/FileSelecter.py
EopTool/interface/InterfaceState.py
EopTool/interface/MainWindow.py
EopTool/interface/ParameterEntry.py
EopTool/interface/ParameterView.py
EopTool/interface/Plot.py
EopTool/interface/SigmaEntry.py
EopTool/interface/__init__.py
EopTool/resources/__init__.py
EopTool/resources/ut1ls.dat
HelmertTool/__init__.py
HelmertTool/__main__.py
HelmertTool/calc.py
HelmertTool/io.py
HelmertTool/units.py
HelmertTool/visualise.py
HelmertTool/interface/FileSelecter.py
HelmertTool/interface/InterfaceState.py
HelmertTool/interface/MainWindow.py
HelmertTool/interface/ParameterEntry.py
HelmertTool/interface/ParameterView.py
HelmertTool/interface/Plot.py
HelmertTool/interface/SelectStations.py
HelmertTool/interface/__init__.py
HelmertTool/resources/__init__.py
HelmertTool/resources/map.png
HelmertTool/resources/transform_sites.txt
IcrfTool/__init__.py
IcrfTool/__main__.py
IcrfTool/calc.py
IcrfTool/io.py
IcrfTool/units.py
IcrfTool/visualisation.py
IcrfTool/interface/FileSelecter.py
IcrfTool/interface/InterfaceState.py
IcrfTool/interface/MainWindow.py
IcrfTool/interface/ParameterEntry.py
IcrfTool/interface/ParameterViewA.py
IcrfTool/interface/ParameterViewB.py
IcrfTool/interface/Plot.py
IcrfTool/interface/SelectStations.py
IcrfTool/interface/__init__.py
adrians_geotools-0.0.1.dist-info/LICENSE
adrians_geotools-0.0.1.dist-info/METADATA
adrians_geotools-0.0.1.dist-info/WHEEL
adrians_geotools-0.0.1.dist-info/entry_points.txt
adrians_geotools-0.0.1.dist-info/top_level.txt
adrians_geotools-0.0.1.dist-info/RECORD
