Metadata-Version: 2.1
Name: adrians-geotools
Version: 0.0.1
Summary: UNKNOWN
Home-page: UNKNOWN
License: UNKNOWN
Platform: UNKNOWN
License-File: LICENSE
Requires-Dist: python-version (>="3.8")
Requires-Dist: numpy (>=1.21.1)
Requires-Dist: pandas (>=1.3.1)
Requires-Dist: matplotlib (>=3.4.2)
